vpr_parser/__init__.py
vpr_parser/models.py
vpr_parser/parser.py
vpr_parser/utils.py
vpr_parser-0.1.0.dist-info/licenses/LICENSE
vpr_parser-0.1.0.dist-info/METADATA
vpr_parser-0.1.0.dist-info/WHEEL
vpr_parser-0.1.0.dist-info/top_level.txt
vpr_parser-0.1.0.dist-info/RECORD
