Metadata-Version: 2.4
Name: vpr-parser
Version: 0.1.0
Summary: Pydantic-based VOCALOID5 Editor Project (.vpr) file parser & unparser
Requires-Python: >=3.11
License-File: LICENSE
Dynamic: license-file
